<Properties StartupConfiguration="{22A98D81-8044-40BF-9EDE-E308A65380C2}|Default">
  <MultiItemStartupConfigurations />
  <MonoDevelop.Ide.DebuggingService.PinnedWatches />
  <MonoDevelop.Ide.DebuggingService.Breakpoints>
    <BreakpointStore />
  </MonoDevelop.Ide.DebuggingService.Breakpoints>
  <MonoDevelop.Ide.Workspace ActiveConfiguration="Debug" />
  <MonoDevelop.Ide.Workbench ActiveDocument="Final_Project/Classes/Encounter.cs">
    <Files>
      <File FileName="Final_Project/Classes/Entities/IEntity.cs" />
      <File FileName="Final_Project/Classes/Actions/Attack.cs" />
      <File FileName="Final_Project/Classes/Actions/Weapon.cs" />
      <File FileName="Final_Project/Classes/Entities/Entity.cs" />
      <File FileName="Final_Project/Classes/Entities/Enemies/Bosses/Mistral.cs" />
      <File FileName="Final_Project/Classes/Entities/Enemies/Bosses/Sundowner.cs" />
      <File FileName="Final_Project/Classes/Entities/Enemies/Bosses/Armstrong.cs" />
      <File FileName="Final_Project/Classes/Entities/IAttacker.cs" />
      <File FileName="Final_Project/Classes/Entities/Enemies/Cyborg.cs" />
      <File FileName="Final_Project/Classes/Entities/Player.cs" />
      <File FileName="Final_Project/Classes/Menu/EncounterMenu.cs" />
      <File FileName="Final_Project/Classes/Menu/StoreMenu.cs" />
      <File FileName="Final_Project/Classes/Game.cs" />
      <File FileName="Final_Project/Classes/Menu/Menu.cs" />
      <File FileName="Final_Project/Classes/Entities/Enemies/Bosses/JetstreamSam.cs" />
      <File FileName="Final_Project/Classes/Entities/Enemies/Bosses/Monsoon.cs" />
      <File FileName="Final_Project/Classes/Entities/Enemies/Bosses/BladeWolf.cs" />
      <File FileName="Final_Project/Program.cs" />
      <File FileName="Final_Project/Classes/Encounter.cs" Line="177" Column="10" />
    </Files>
    <Pads>
      <Pad Id="ProjectPad">
        <State name="__root__">
          <Node name="Final_Project" expanded="True">
            <Node name="Final_Project" expanded="True">
              <Node name="Classes" expanded="True">
                <Node name="Actions" expanded="True" />
                <Node name="Entities" expanded="True">
                  <Node name="Enemies" expanded="True">
                    <Node name="Bosses" expanded="True" />
                  </Node>
                </Node>
                <Node name="Menu" expanded="True" />
              </Node>
            </Node>
          </Node>
        </State>
      </Pad>
    </Pads>
  </MonoDevelop.Ide.Workbench>
  <MonoDevelop.Ide.ItemProperties.Final__Project PreferredExecutionTarget="MonoDevelop.Default" />
</Properties>